setup.py
distributions_python_py/Binomialdistribution.py
distributions_python_py/Gaussiandistribution.py
distributions_python_py/Generaldistribution.py
distributions_python_py/__init__.py
distributions_python_py.egg-info/PKG-INFO
distributions_python_py.egg-info/SOURCES.txt
distributions_python_py.egg-info/dependency_links.txt
distributions_python_py.egg-info/not-zip-safe
distributions_python_py.egg-info/top_level.txt